<?xml version="1.0" encoding="UTF-8"?>

<shop_config>

	<!--
	
		prices="1.99$ x 100"
		
	-->

	<item id="50"  sku="iap_vegasol_roulette" prices="99"     add_vip_exp="100" view_type="ROULETTE" />

	<item id="100" sku="iap_vegasol_first"   prices="99"     add_vip_exp="100" base_money="200000"   only_one="PLAYER_FLAG_FIRST_RECHARGE"  view_type="NEWBIE"/>

	<item id="101" sku="iap_vegasol_newbie"   prices="99"     add_vip_exp="100" base_money="200000"   only_one="PLAYER_FLAG_FIRST_RECHARGE"  view_type="NEWBIE">
		<prop tid="5001002" num="7" />
		<prop tid="5001004" num="3" />
		<prop tid="5001005" num="7" />
		<prop tid="5001008" num="7" />
		<prop tid="5001009" num="3" />
	</item>
	
	<item id="102" sku="iap_vegasol_newbie2"   prices="499"     add_vip_exp="500" base_money="1000000"   only_one="PLAYER_FLAG_FIRST_RECHARGE"  view_type="NEWBIE">
		<prop tid="5001002" num="15" />
		<prop tid="5001004" num="5" />
		<prop tid="5001005" num="15" />
		<prop tid="5001008" num="15" />
	</item>
	
	
	<item id="200" sku="iap_vegasol_d1"       prices="199"    add_vip_exp="200" base_money="40000"  bonus="3" open_minute="30"  view_type="DEAL" />
	<item id="201" sku="iap_vegasol_d2"       prices="499"    add_vip_exp="200" base_money="100000"  bonus="3" open_minute="30"  view_type="DEAL" />
	<item id="202" sku="iap_vegasol_d7"       prices="699"    add_vip_exp="200" base_money="150000"  bonus="3" open_minute="30"  view_type="DEAL" />
	<item id="203" sku="iap_vegasol_d3"       prices="999"    add_vip_exp="200" base_money="200000"  bonus="3" open_minute="30"  view_type="DEAL" />
	<item id="204" sku="iap_vegasol_d4"       prices="1999"   add_vip_exp="200" base_money="800000"  bonus="3" open_minute="30"  view_type="DEAL" />
	<item id="211" sku="iap_vegasol_d11"      prices="199"    add_vip_exp="200" base_money="40000"  bonus="5" open_minute="30"  view_type="DEAL" />
	<item id="212" sku="iap_vegasol_d12"      prices="499"    add_vip_exp="200" base_money="100000"  bonus="5" open_minute="30"  view_type="DEAL" />
	<item id="213" sku="iap_vegasol_d17"      prices="699"    add_vip_exp="200" base_money="150000"  bonus="5" open_minute="30"  view_type="DEAL" />
	<item id="214" sku="iap_vegasol_d13"      prices="999"    add_vip_exp="200" base_money="200000"  bonus="5" open_minute="30"  view_type="DEAL" />
	<item id="215" sku="iap_vegasol_d14"      prices="1999"   add_vip_exp="200" base_money="800000"  bonus="5" open_minute="30"  view_type="DEAL" />
	
	<item id="300" sku="iap_vegasol_p1"       prices="199"   add_vip_exp="200"   view_type="PIG" />
	<item id="301" sku="iap_vegasol_p2"       prices="499"   add_vip_exp="500"   view_type="PIG" />
	<item id="302" sku="iap_vegasol_p3"       prices="999"   add_vip_exp="1000"  view_type="PIG" />
	<item id="303" sku="iap_vegasol_p5"       prices="4999"  add_vip_exp="5000"  view_type="PIG" />
	
	<item id="310" sku="iap_vegasol_p11"      prices="199"   add_vip_exp="200"   bonus="2"    view_type="PIG" />
	<item id="311" sku="iap_vegasol_p12"      prices="499"   add_vip_exp="500"   bonus="2"    view_type="PIG" />
	<item id="312" sku="iap_vegasol_p13"      prices="999"   add_vip_exp="1000"  bonus="2"    view_type="PIG" />
	<item id="313" sku="iap_vegasol_p15"      prices="4999"  add_vip_exp="5000"  bonus="2"    view_type="PIG" />
	
	
	<!-- 
			购买到的钱 = base_money * bonus * vip加成 
			
			<item id="506" sku="iap_vegasol_c7" prices="699" view_type="SHOP" />
	-->

	<item id="500" sku="iap_vegasol_c1" weight="10" prices="199"    add_vip_exp="200"     base_money="40000"       view_type="SHOP" />
	<item id="501" sku="iap_vegasol_c2" weight="20" prices="499"    add_vip_exp="500"     base_money="100000"      view_type="SHOP" />
	<item id="502" sku="iap_vegasol_c3" weight="30" prices="999"    add_vip_exp="1000"    base_money="200000"      view_type="SHOP" />
	<item id="503" sku="iap_vegasol_c4" weight="40" prices="1999"   add_vip_exp="2000"    base_money="800000"      view_type="SHOP" sale_pic="Popular" />
	<item id="504" sku="iap_vegasol_c5" weight="50" prices="4999"   add_vip_exp="5000"    base_money="2200000"     view_type="SHOP" />
	<item id="505" sku="iap_vegasol_c6" weight="60" prices="9999"   add_vip_exp="10000"   base_money="5000000"     view_type="SHOP" sale_pic="Best" />
	

	<item id="600" sku="iap_vegasol_c300" weight="10" prices="199"    add_vip_exp="200"     base_rmb="200"     rmb_bonus="1"    view_type="SHOP_RMB" />
	<item id="601" sku="iap_vegasol_c301" weight="20" prices="499"    add_vip_exp="500"     base_rmb="500"     rmb_bonus="1"    view_type="SHOP_RMB" />
	<item id="602" sku="iap_vegasol_c302" weight="30" prices="999"    add_vip_exp="1000"     base_rmb="1000"     rmb_bonus="1"    view_type="SHOP_RMB" />
	<item id="603" sku="iap_vegasol_c303" weight="40" prices="1999"    add_vip_exp="2000"     base_rmb="4000"     rmb_bonus="1"    view_type="SHOP_RMB" />
	<item id="604" sku="iap_vegasol_c304" weight="50" prices="4999"    add_vip_exp="5000"     base_rmb="11000"     rmb_bonus="1"    view_type="SHOP_RMB" />
	<item id="605" sku="iap_vegasol_c305" weight="60" prices="9999"    add_vip_exp="10000"     base_rmb="25000"     rmb_bonus="1"    view_type="SHOP_RMB" />
	
	<!--
	<sale weight="1" open_time="19:30:00"  duration_minute="200" >
	
		<item   id="500"  weight="90"  bonus="1.2"/>
		<item   id="501"  weight="100" bonus="2.7"/>

	</sale>

	<sale weight="10" open_time="2015-10-28 19:40:00"  duration_minute="200" >
	
		<item   id="500"  weight="100"  bonus="1.5"/>
		
	</sale>
	-->
	
	<pig id="1" in_rate="1" max_return="2000000" replace_min="0" replace_max="1999999"   shop_item_id="300"  pop_condition="2000000" pop_picture="" >
	    <!--
		on_sale_condition 值 顺次增加;
		-->
		<on_sale on_sale_condition="1000000" duration_minute="30" pop_picture="" on_sale_item_id="310" />
		<on_sale on_sale_condition="1500000" duration_minute="30" pop_picture="" on_sale_item_id="310" />
	</pig>
	<pig id="2" in_rate="1" max_return="5000000" replace_min="2000000" replace_max="4999999"   shop_item_id="301"  pop_condition="5000000" pop_picture="" >
		<on_sale on_sale_condition="2500000" duration_minute="30" pop_picture="" on_sale_item_id="311" />
		<on_sale on_sale_condition="3750000" duration_minute="30" pop_picture="" on_sale_item_id="311" />	
	</pig>
	<pig id="3" in_rate="1" max_return="10000000" replace_min="5000000" replace_max="9999999"   shop_item_id="302"  pop_condition="10000000" pop_picture="" >
		<on_sale on_sale_condition="5000000" duration_minute="30" pop_picture="" on_sale_item_id="312" />
		<on_sale on_sale_condition="7500000" duration_minute="30" pop_picture="" on_sale_item_id="312" />	
	</pig>
	<pig id="4" in_rate="1" max_return="110000000" replace_min="10000000" replace_max="0"   shop_item_id="303"  pop_condition="50000000" pop_picture="" >
		<on_sale on_sale_condition="55000000" duration_minute="30" pop_picture="" on_sale_item_id="313" />
		<on_sale on_sale_condition="82500000" duration_minute="30" pop_picture="" on_sale_item_id="313" />	
	</pig>
	
	<!--
	<pig  id="1"  in_rate="1"   max_return="4000000"   replace_min="0"        replace_max="1999999"   shop_item_id="300"  pop_condition="2000000"     on_sale_condition="2000000,3000000"   duration_minute="30"  on_sale_item_id="310"  />
	<pig  id="2"  in_rate="1"   max_return="10000000"  replace_min="2000000"  replace_max="4999999"   shop_item_id="301"  pop_condition="5000000"     on_sale_condition="5000000,6000000"   duration_minute="30"  on_sale_item_id="311"  />
	<pig  id="3"  in_rate="1"   max_return="20000000"  replace_min="5000000"  replace_max="9999999"   shop_item_id="302"  pop_condition="10000000"    on_sale_condition="10000000,20000000" duration_minute="30"  on_sale_item_id="312"  />
	<pig  id="4"  in_rate="1"   max_return="100000000" replace_min="10000000" replace_max="0"         shop_item_id="303"  pop_condition="50000000"    on_sale_condition="50000000,60000000" duration_minute="30"  on_sale_item_id="313"  />
	-->
	
</shop_config>

